protokolo/__init__.py
protokolo/__main__.py
protokolo/_formatter.py
protokolo/_util.py
protokolo/cli.py
protokolo/compile.py
protokolo/config.py
protokolo/exceptions.py
protokolo/i18n.py
protokolo/initialise.py
protokolo/locale/fr/LC_MESSAGES/protokolo.mo
protokolo/locale/nb_NO/LC_MESSAGES/protokolo.mo
protokolo/locale/nl/LC_MESSAGES/protokolo.mo
protokolo/locale/ta/LC_MESSAGES/protokolo.mo
protokolo/py.typed
protokolo/replace.py
protokolo/types.py
protokolo-3.0.2.dist-info/LICENSES/CC-BY-SA-4.0.txt
protokolo-3.0.2.dist-info/LICENSES/CC0-1.0.txt
protokolo-3.0.2.dist-info/LICENSES/EUPL-1.2.txt
protokolo-3.0.2.dist-info/METADATA
protokolo-3.0.2.dist-info/WHEEL
protokolo-3.0.2.dist-info/entry_points.txt
protokolo-3.0.2.dist-info/RECORD
