Metadata-Version: 2.1
Name: protokolo
Version: 3.0.2
Summary: Protokolo is a change log generator.
Home-page: https://codeberg.org/carmenbianca/protokolo
License: EUPL-1.2+
Keywords: changelog,history,news
Author: Carmen Bianca BAKKER
Author-email: carmen@carmenbianca.eu
Maintainer: Carmen Bianca BAKKER
Maintainer-email: carmen@carmenbianca.eu
Requires-Python: >=3.11
Classifier: Intended Audience :: Developers
Classifier: License :: Other/Proprietary License
Classifier: Programming Language :: Python :: 3
Classifier: Programming Language :: Python :: 3.11
Classifier: Programming Language :: Python :: 3.12
Classifier: Programming Language :: Python :: 3.13
Classifier: Topic :: Documentation
Classifier: Topic :: Software Development :: Documentation
Classifier: Topic :: Utilities
Requires-Dist: attrs (>=22.1.0)
Requires-Dist: click (>=8.0)
Project-URL: Documentation, https://protokolo.readthedocs.io
Project-URL: Repository, https://codeberg.org/carmenbianca/protokolo
